account_service/__init__.py
account_service/accountService_pb2.py
account_service/accountService_pb2_grpc.py
account_service/common_pb2.py
account_service/common_pb2_grpc.py
account_service/grpc_client.py
account_service/models.py
account_service/schema.py
longleding_account_service_sdk-0.1.5.dist-info/LICENSE
longleding_account_service_sdk-0.1.5.dist-info/METADATA
longleding_account_service_sdk-0.1.5.dist-info/WHEEL
longleding_account_service_sdk-0.1.5.dist-info/top_level.txt
longleding_account_service_sdk-0.1.5.dist-info/RECORD
