Metadata-Version: 2.1
Name: longleding-account-service-sdk
Version: 0.1.5
Summary: Longleding Account Service SDK
Home-page: https://git.emhub.top/em/account-service
Author: Shi Ran
Author-email: ran.shi@longleding.com
License: UNKNOWN
Platform: UNKNOWN
Classifier: Programming Language :: Python :: 3
Classifier: Topic :: System :: Logging
Requires-Python: >=3.6
Requires-Dist: attrs
Requires-Dist: marshmallow
